{
    "GEJALA": [
        "cemas",
        "cemas yang ringan",
        "gelisah",
        "impulsive",
        "iritabilitas",
        "khawatir berlebihan",
        "kurang konsisten dalam sikap atau keputusan",
        "kurang mampu menerima kesalahan",
        "kurang percaya diri",
        "kurang yakin terhadap nilai dirinya",
        "labil",
        "melihat diri sendiri dengan cara yang tidak baik",
        "memasang standar diri tinggi",
        "memikirkan berbagai kemungkinan buruk",
        "menunjukan kebutuhan untuk diperehatikan dan ddiakui",
        "overthinking",
        "perasaan belum cukup baik terhadap dirinya",
        "perfeksionis",
        "sensitive terhadap penilaian orang lain",
        "sering memikirkan berbagai kemungkinan buruk",
        "sering merasa kecewa",
        "sikap yang tegas bahkan agak keras",
        "suana hatinya cukup mudah berubah",
        "suasana hatinya sesekali dapat berubah mengikuti situasi",
        "suka memendam perasaan",
        "sulit bergaul dengan orang",
        "sulit mengungkapkan isi pikiran",
        "sulit rileks",
        "sulit untuk rileks",
        "susah beradaptasi",
        "tegang",
        "tempramen"
    ],
    "DIAGNOSIS": [],
    "TANTANGAN": [
        "belajar memperhatikan perasaan orang lain",
        "beresiko membuat pilihan yang kurang matang",
        "cenderung menyimpan rasa kecewa",
        "ingin diperhatikan dan dihargai",
        "ingin selalu terlihat baik dan benar",
        "kebutuhan akan pengakuan",
        "kekhawatiran berlebihan",
        "kepekaan terhadap orang lain",
        "keraguan terhadap nilai diri",
        "kestailan emosi dan sikap",
        "kurang puas terhadap diri dan keadaan",
        "membangun hubungan yang lebih setara",
        "mengelola dorongan untuk selalu unggul",
        "mengendalikan tindakan yang tergesa-gesa",
        "mudadh merasa tersinggung",
        "mudah merasa kecewa",
        "mudah merasa kesal",
        "percaya diri dan berani tampil",
        "perfeksionisme yang membebani",
        "perlu belajar menerima",
        "perlu mengembangkan rasa percaya diri yang bukan dari pengakuan orang lain",
        "sauna hati bisa berubah jika tidak mendapatkan perhatian atau dihargai",
        "sering menahan perasaan",
        "sesekali merasa belum cukup baik",
        "standar diri yang cenderung tinggi",
        "suka merasa kecewa pada diri sendiri",
        "sulit menikmati pencapaian",
        "sulit merasa bebas menjadi dirinya sendiri",
        "sulit merasa tenang",
        "tekanan untuk menjada citra diri",
        "terlalu focus pada pengakuan",
        "terlalu keras pada diri sendiri",
        "tetap tenang apabila respons orang tidak sesuai harapan"
    ],
    "KEKUATAN": [
        "bekerja secara terarah",
        "berani mengambil peluang",
        "berpikir luas",
        "bersemangat, penuh energi, dan spontan",
        "bertanggung jawab",
        "berusaha tampil konsisten",
        "bisa dipercaya",
        "ceria dan mudah bergaul",
        "daya dorong yang kuat",
        "disiplin dalam menjalankan tanggung jawab",
        "energi dan semangat tinggi",
        "inisiatif",
        "kemampuan komunikasi yang hidup",
        "kemampuan untuk mengorganisasi diri",
        "keyakinannya pada diri sendiri",
        "mampu bekerja dibawah suasana hati yang kurang baik",
        "mampu membangun kesan menyenangkan",
        "mampu membaw energi positif dalam kelompok",
        "mampu mengendalikan diri",
        "mampu mengendalikan diri dan menjaga sikap agar tetap rapi",
        "mampu menjaga jarak secara emosional",
        "mampu menjaga jarak yang sehat dalam hubungan",
        "mampu menjaga tanggung jawab",
        "mampu tampil disiplin dan dapat diandalkan",
        "mampu tampil percaya diri dan menyenangkan",
        "memandirian dalam mengambil sikap",
        "memiliki dorongan untuk berkembang",
        "memiliki keinginan untuk berkembang",
        "memiliki kemampuan untuk memahami orang lain",
        "memiliki kesadaran kan diri sendiri",
        "memiliki perhatian yang baik terhadap detail",
        "mencapai target besar",
        "menginspirasi orang lain",
        "menjaga citra sebagai orang yang bertanggung jawab",
        "menjaga sikap dan perilaku sehingga jarang bertindak berlebihan",
        "menyukai eteraturan dan kejelasan",
        "mudah membayangkan rencana besar",
        "peka terhadap orang lain",
        "peka terhadap suasana",
        "penuh percaya diri dan berani mengambil posisi yang menonjol",
        "percaya diri dan berani tampil",
        "percaya dirii untuk memimpin",
        "produktif",
        "rapi, teratur, dan bertanggung jawab",
        "rapih",
        "sangat disiplin dalam menjalankan tugas",
        "sangat percaya pada kemampuan dan penilaiannya sendiri",
        "selalu berusaha menyelesaikan ugas dengan baik",
        "tekun",
        "tidak mudah bergantung pada orang lain",
        "tidak mudah merasa kecil",
        "tidak mudah terpengaruh tekanan",
        "yakin dengan ide-idenya"
    ],
    "REKOMENDASI": [
        "belajar berhenti sejenak sebelum bereaksi",
        "belajar memberi penghargaan pada dirinya sendiri tanpa harus menunggu pengakuan dari orang lain",
        "belajar memberi ruang untuk menerima kekurangan",
        "belajar menerima diri apa adanya",
        "berbagi perasaan dengan orang terdekat",
        "berbicara dengan orang yang dipercaya",
        "biasakan membuat jeda sebelum mengambil keputusan penting",
        "cari kegiatan yang membantu menenangkan pikiran",
        "focus pada proses dan kualitas kerja",
        "kelola stress",
        "latih diri untuk lebih mendengarkan orang lain tanpa langsung, membandingkan atau mempertahankan diri",
        "melatih kesadaran diri saat emosinya berubah",
        "melatik menerima kesalahan ebagai bagian dari proses belajar",
        "membangun kebiasaan mendengarkan dengan sungguh - sungguh",
        "membiasakan ddiri mencatat hal-hal positif",
        "mempelajari teknis relaksasi",
        "menerima bahwa kesalahan tidak membuat nilai dirinya berkurang",
        "mengembangkan asa percaya diri yang bersumber dari pencapaian nyata, bukan hanya dari pujian ataua perhatian",
        "menjaga kesehatan fisik",
        "menjaga rutinitas yang terataur",
        "menyalurkan kebutuhan untuk tampil dan dihargai melalui kegiatan positif",
        "mmenyampaikan perasaan secara lebih terbuka",
        "perlu belajar menerima bahwa tidak semua hal harus sempurna"
    ]
}